djpyfs/__init__.py
djpyfs/djpyfs.py
djpyfs/models.py
djpyfs/tests.py
openedx_django_pyfs-3.8.0.dist-info/licenses/LICENSE
openedx_django_pyfs-3.8.0.dist-info/METADATA
openedx_django_pyfs-3.8.0.dist-info/WHEEL
openedx_django_pyfs-3.8.0.dist-info/top_level.txt
openedx_django_pyfs-3.8.0.dist-info/RECORD
