Metadata-Version: 2.4
Name: openedx-django-pyfs
Version: 3.8.0
Summary: Django pyfilesystem integration
Home-page: https://github.com/openedx/django-pyfs
Author: Open edX
Author-email: oscm@tcril.org
License: Apache 2.0
Classifier: Development Status :: 4 - Beta
Classifier: Framework :: Django
Classifier: Framework :: Django :: 4.2
Classifier: Framework :: Django :: 5.1
Classifier: Framework :: Django :: 5.2
Classifier: Programming Language :: Python
Classifier: Programming Language :: Python :: 3
Classifier: Programming Language :: Python :: 3.11
Classifier: Programming Language :: Python :: 3.12
Classifier: Topic :: Software Development :: Libraries :: Python Modules
Classifier: License :: OSI Approved :: Apache Software License
License-File: LICENSE
Requires-Dist: django
Requires-Dist: fs>=2.0.1
Requires-Dist: fs-s3fs
Dynamic: author
Dynamic: author-email
Dynamic: classifier
Dynamic: description
Dynamic: description-content-type
Dynamic: home-page
Dynamic: license
Dynamic: license-file
Dynamic: requires-dist
Dynamic: summary
